LICENSE
MANIFEST.in
README.rst
setup.py
handy/__init__.py
handy/ajax.py
handy/cross.py
handy/db.py
handy/decorators.py
handy/http.py
handy/logger.py
handy/mail.py
handy/middleware.py
handy/shortcuts.py
handy/text.py
handy/utils.py
handy.egg-info/PKG-INFO
handy.egg-info/SOURCES.txt
handy.egg-info/dependency_links.txt
handy.egg-info/pbr.json
handy.egg-info/requires.txt
handy.egg-info/top_level.txt
handy/forms/__init__.py
handy/forms/widgets.py
handy/models/__init__.py
handy/models/encode.py
handy/models/fields.py